setup.py
ruruki_eye/VERSION
ruruki_eye/__init__.py
ruruki_eye/server.py
ruruki_eye.egg-info/PKG-INFO
ruruki_eye.egg-info/SOURCES.txt
ruruki_eye.egg-info/dependency_links.txt
ruruki_eye.egg-info/requires.txt
ruruki_eye.egg-info/top_level.txt
ruruki_eye/static/graph.html
ruruki_eye/static/search.html
ruruki_eye/static/css/bootstrap.min.css
ruruki_eye/static/css/ruruki-eye.css
ruruki_eye/static/fonts/LICENSE.txt
ruruki_eye/static/fonts/OpenSans-Light.ttf
ruruki_eye/static/fonts/OpenSans-Regular.ttf
ruruki_eye/static/fonts/glyphicons-halflings-regular.eot
ruruki_eye/static/fonts/glyphicons-halflings-regular.svg
ruruki_eye/static/fonts/glyphicons-halflings-regular.ttf
ruruki_eye/static/fonts/glyphicons-halflings-regular.woff
ruruki_eye/static/fonts/glyphicons-halflings-regular.woff2
ruruki_eye/static/img/favicon.ico
ruruki_eye/static/img/glyphicons-halflings-white.png
ruruki_eye/static/img/glyphicons-halflings.png
ruruki_eye/static/img/rurukieye_logo.png
ruruki_eye/static/js/bootstrap.min.js
ruruki_eye/static/js/d3.v3.js
ruruki_eye/static/js/dust-full.min.js
ruruki_eye/static/js/jquery-2.1.4.min.js
ruruki_eye/static/js/ruruki-eye.js