Metadata-Version: 1.1
Name: ruruki-eye
Version: 0.1.1
Summary: Ruruki Eye is a visualizer for Ruruki (In Memory Graph Tool)
Home-page: UNKNOWN
Author: Andre F. Macedo
Author-email: andre.macedo _at_ optiver.com.au
License: UNKNOWN
Keywords: graph db memory interactive eye visualizer web
Platform: UNKNOWN
Classifier: Development Status :: 4 - Beta
Classifier: License :: OSI Approved :: Apache Software License
Classifier: Intended Audience :: Developers
Classifier: Intended Audience :: Information Technology
Classifier: Framework :: Flask
Classifier: Programming Language :: Python :: 2.7
Classifier: Programming Language :: Python :: 2 :: Only
Classifier: Topic :: Database :: Database Engines/Servers
Classifier: Topic :: Software Development :: Libraries
